agent_watch/__init__.py
agent_watch/cost_calculator.py
agent_watch/logger.py
agent_watch/monitor.py
agent_watch/utils.py
agent_watch/visualizer.py
tests/__init__.py
tests/test_agent_watch.py
agent_watch-0.1.1.dist-info/LICENSE
agent_watch-0.1.1.dist-info/METADATA
agent_watch-0.1.1.dist-info/WHEEL
agent_watch-0.1.1.dist-info/top_level.txt
agent_watch-0.1.1.dist-info/RECORD
