Metadata-Version: 2.1
Name: agent-watch
Version: 0.1.1
Summary: An operational monitoring library for Crew AI applications.
Home-page: https://github.com/AIAnytime/agent-watch
Author: AI Anytime
Author-email: sonu@aianytime.net
Classifier: Programming Language :: Python :: 3
Classifier: License :: OSI Approved :: MIT License
Classifier: Operating System :: OS Independent
Requires-Python: >=3.8
License-File: LICENSE
Requires-Dist: psutil
Requires-Dist: matplotlib
Requires-Dist: streamlit
Requires-Dist: tiktoken
